vector_khing/__init__.py
vector_khing/vec2d.py
khingproject-0.1.1.dist-info/METADATA
khingproject-0.1.1.dist-info/WHEEL
khingproject-0.1.1.dist-info/top_level.txt
khingproject-0.1.1.dist-info/RECORD
