Metadata-Version: 2.4
Name: khingproject
Version: 0.1.1
Summary: This is my first project.Use to calculate dot product,cross product, and magnitude of vector.
Home-page: https://github.com/khing2005/khingproject
Author: khing
Author-email: anchitha2005@gmail.com
Requires-Python: >=3.7
Dynamic: author
Dynamic: author-email
Dynamic: description
Dynamic: description-content-type
Dynamic: home-page
Dynamic: requires-python
Dynamic: summary
